.travis.yml
AUTHORS
ChangeLog
LICENSE
MANIFEST.in
README.md
requirements.txt
setup.cfg
setup.py
test-requirements.txt
tox.ini
eh/__init__.py
eh/autocomplete.py
eh/cli.py
eh/config.py
eh/constants.py
eh/exceptions.py
eh/git_store.py
eh/output.py
eh/topic.py
eh/topic_key.py
eh/topic_manager.py
eh/topic_store.py
eh.egg-info/PKG-INFO
eh.egg-info/SOURCES.txt
eh.egg-info/dependency_links.txt
eh.egg-info/entry_points.txt
eh.egg-info/not-zip-safe
eh.egg-info/pbr.json
eh.egg-info/requires.txt
eh.egg-info/top_level.txt
eh/contrib/__init__.py
eh/contrib/subjects/eh/about.md
eh/contrib/subjects/eh/future.md
eh/contrib/subjects/eh/help.md
eh/contrib/subjects/eh/install.md
eh/contrib/subjects/eh/topics.md
eh/contrib/subjects/eh/testing/woo.md
eh/tests/__init__.py
eh/tests/base_test.py
eh/tests/test_git_store.py
eh/tests/test_topic.py
eh/tests/test_topic_key.py
eh/tests/test_topic_manager.py
eh/tests/test_topic_store.py