Metadata-Version: 2.1
Name: eh
Version: 1.4.2
Summary: A command line program that will output helpful reminders based on parameters
Home-page: http://github.com/roaet/eh
Author: Justin L. Hammond
Author-email: runningempty@gmail.com
License: Apache-2
Platform: UNKNOWN
Classifier: Development Status :: 5 - Production/Stable
Classifier: Environment :: Console
Classifier: Intended Audience :: Developers
Classifier: Intended Audience :: Information Technology
Classifier: License :: OSI Approved :: Apache Software License
Classifier: Operating System :: OS Independent
Classifier: Programming Language :: Python
